chunli/__init__.py
chunli/app.py
chunli/call.py
chunli/caller.py
chunli/exceptions.py
chunli/_tests/test_rps_for_rampup.py
chunli-0.11.3.dist-info/WHEEL
chunli-0.11.3.dist-info/METADATA
chunli-0.11.3.dist-info/RECORD
