Metadata-Version: 2.1
Name: chunli
Version: 0.11.3
Summary: chunli
Home-page: https://github.com/luizalabs/chunli
License: UNKNOWN
Author: Recommedations Squad
Author-email: bob@luizalabs.com
Requires-Python: >=3.8
Requires-Dist: apidaora
Requires-Dist: confdaora
Requires-Dist: aioredis
Requires-Dist: httpx
Requires-Dist: numpy
Requires-Dist: redis
Requires-Dist: gunicorn
Requires-Dist: uvicorn
Requires-Dist: hiredis
Requires-Dist: cython
Requires-Dist: mkdocs ; extra == "doc"
Requires-Dist: mkdocs-material ; extra == "doc"
Requires-Dist: markdown-include ; extra == "doc"
Requires-Dist: black ; extra == "test"
Requires-Dist: bumpversion ; extra == "test"
Requires-Dist: flake8 ; extra == "test"
Requires-Dist: isort ; extra == "test"
Requires-Dist: ipython ; extra == "test"
Requires-Dist: mypy ; extra == "test"
Requires-Dist: pytest-cov ; extra == "test"
Requires-Dist: pytest-mock ; extra == "test"
Requires-Dist: pytest>=5.1.1 ; extra == "test"
Project-URL: Documentation, https://luizalabs.github.io/chunli/
Provides-Extra: doc
Provides-Extra: test
